chaosgandi/__init__.py
chaosgandi/domains/__init__.py
chaosgandi/domains/probes.py
chaosgandi/domains/tolerances.py
chaostoolkit_gandi-0.2.0.dist-info/LICENSE
chaostoolkit_gandi-0.2.0.dist-info/METADATA
chaostoolkit_gandi-0.2.0.dist-info/WHEEL
chaostoolkit_gandi-0.2.0.dist-info/top_level.txt
chaostoolkit_gandi-0.2.0.dist-info/RECORD
